openbroker/__init__.py
openbroker/api/__init__.py
openbroker/api/base.py
openbroker/api/instruments.py
openbroker/api/orders.py
openbroker/api/user.py
openbroker/api/ws.py
openbroker/broker.py
openbroker/broker_login.py
openbroker/client.py
openbroker/config.py
openbroker/constant/__init__.py
openbroker/constant/broker.py
openbroker/constant/instrument.py
openbroker/constant/order.py
openbroker/datatype/__init__.py
openbroker/datatype/instrument.py
openbroker/datatype/order.py
openbroker/entity/__init__.py
openbroker/entity/broker.py
openbroker/entity/order.py
openbroker/exceptions.py
openbroker/instrument.py
openbroker/order.py
openbroker/session.py
openbroker/utils.py
openbroker-0.1.1.dist-info/LICENSE
openbroker-0.1.1.dist-info/METADATA
openbroker-0.1.1.dist-info/WHEEL
openbroker-0.1.1.dist-info/RECORD
