Metadata-Version: 2.1
Name: openbroker
Version: 0.1.1
Summary: The first unified API for algo-trading on Indian markets - by AlgoTest
License: MIT
Author: rajat499
Requires-Python: >=3.8,<4.0
Classifier: License :: OSI Approved :: MIT License
Classifier: Programming Language :: Python :: 3
Classifier: Programming Language :: Python :: 3.8
Classifier: Programming Language :: Python :: 3.9
Classifier: Programming Language :: Python :: 3.10
Classifier: Programming Language :: Python :: 3.11
Requires-Dist: pyotp (>=2.8.0,<3.0.0)
Requires-Dist: requests (>=2.31.0,<3.0.0)
Requires-Dist: urllib3 (>=2.1.0,<3.0.0)
Requires-Dist: websocket-client (>=1.3.2,<2.0.0)
